marock/__init__.py
marock-0.1.0.dist-info/licenses/LICENSE
marock-0.1.0.dist-info/METADATA
marock-0.1.0.dist-info/WHEEL
marock-0.1.0.dist-info/top_level.txt
marock-0.1.0.dist-info/RECORD
