Metadata-Version: 2.4
Name: marock
Version: 0.1.0
Summary: Marock allows you to colour up your texts
Author: Marcy
License: MIT
Requires-Python: >=3.7
License-File: LICENSE
Dynamic: license-file
Dynamic: requires-python
